HISTORY.rst
LICENSE
MANIFEST.in
README.rst
setup.py
docs/Makefile
docs/api.rst
docs/conf.py
docs/index.rst
docs/make.bat
docs/user/flask_quickstart.rst
docs/user/intro.rst
docs/user/providers.rst
tests/test_ipizza.py
wirexfers/__init__.py
wirexfers/exc.py
wirexfers/request.py
wirexfers/response.py
wirexfers/utils.py
wirexfers.egg-info/PKG-INFO
wirexfers.egg-info/SOURCES.txt
wirexfers.egg-info/dependency_links.txt
wirexfers.egg-info/requires.txt
wirexfers.egg-info/top_level.txt
wirexfers/providers/__init__.py
wirexfers/providers/ipizza.py
wirexfers/providers/tupas.py