Metadata-Version: 1.1
Name: wirexfers
Version: 0.1
Summary: Simple API for IPizza Solo/TUPAS payment protocols.
Home-page: http://plaes.org/projects/wirexfers
Author: Priit Laes
Author-email: plaes@plaes.org
License: Copyright (c) 2012 Priit Laes.
